pygxusthjw/__init__.py
pygxusthjw/commons/__init__.py
pygxusthjw/commons/array_utils.py
pygxusthjw/commons/data_table.py
pygxusthjw/commons/file_helpers.py
pygxusthjw/commons/file_reader.py
pygxusthjw/commons/gxusthjw_base.py
pygxusthjw/commons/math_plus.py
pygxusthjw/commons/numerical_constant.py
pygxusthjw/commons/numpy_plus.py
pygxusthjw/commons/object_utils.py
pygxusthjw/commons/path_utils.py
pygxusthjw/commons/statistical_interval.py
pygxusthjw/commons/test_array_utils.py
pygxusthjw/commons/test_data_table.py
pygxusthjw/commons/test_file_helpers.py
pygxusthjw/commons/test_gxusthjw_base.py
pygxusthjw/commons/test_math_plus.py
pygxusthjw/commons/test_numerical_constant.py
pygxusthjw/commons/test_numpy_plus.py
pygxusthjw/commons/test_object_utils.py
pygxusthjw/commons/test_path_utils.py
pygxusthjw/commons/test_statistical_interval.py
pygxusthjw/findpeaks/__init__.py
pygxusthjw/fityk_helpers/__init__.py
pygxusthjw/mathematics/__init__.py
pygxusthjw/origin_helpers/__init__.py
pygxusthjw/peakfit_helpers/__init__.py
pygxusthjw/pyaxs/__init__.py
pygxusthjw/pyfityk/__init__.py
pygxusthjw/pyfsd/__init__.py
pygxusthjw/pyftir/__init__.py
pygxusthjw/pyma/__init__.py
pygxusthjw/pymatlab/__init__.py
pygxusthjw/pynmr/__init__.py
pygxusthjw/pyta/__init__.py
pygxusthjw/pyxrd/__init__.py
pygxusthjw/pyzhxyao/__init__.py
pygxusthjw/spectrum/__init__.py
pygxusthjw/units/__init__.py
pygxusthjw-202310312048.dist-info/LICENSE
pygxusthjw-202310312048.dist-info/METADATA
pygxusthjw-202310312048.dist-info/WHEEL
pygxusthjw-202310312048.dist-info/top_level.txt
pygxusthjw-202310312048.dist-info/RECORD
