Metadata-Version: 2.1
Name: pygxusthjw
Version: 202310312048
Summary: the python libraries of gxusthjw.
Home-page: https://codeup.aliyun.com/653e054e940b4e1cb0ceaa17/Python/gxusthjw-pypackages
Author: gxusthjw
Author-email: jiweihuang@vip.163.com
License: MIT
Classifier: Topic :: Software Development :: Libraries :: Python Modules
Classifier: Programming Language :: Python
Classifier: Programming Language :: Python :: 3
Classifier: Programming Language :: Python :: 3.7
Classifier: Programming Language :: Python :: 3.8
Classifier: Programming Language :: Python :: 3.9
Classifier: Programming Language :: Python :: 3.10
Classifier: Programming Language :: Python :: 3.11
Classifier: Programming Language :: Python :: 3.12
Classifier: Programming Language :: Python :: Implementation :: CPython
License-File: LICENSE
Requires-Dist: numpy
Requires-Dist: scipy
Requires-Dist: pandas
Requires-Dist: matplotlib
Requires-Dist: statsmodels
Requires-Dist: lmfit
Requires-Dist: pyampd
Requires-Dist: ampdLib
Requires-Dist: findiff
Requires-Dist: numdifftools
Requires-Dist: pybaselines
Requires-Dist: pytest
Requires-Dist: chardet
